fftools/__about__.py
fftools/__init__.py
fftools/healthchecks.py
fftools/logger.py
fftools/mailer.py
fftools/other.py
fftools/shell.py
fftools/web.py
fftools-2.1.0.dist-info/METADATA
fftools-2.1.0.dist-info/WHEEL
fftools-2.1.0.dist-info/licenses/LICENSE
fftools-2.1.0.dist-info/RECORD
