Metadata-Version: 2.4
Name: fftools
Version: 2.1.0
Summary: 44net tools
Project-URL: Homepage, https://github.com/olofvndrhr/fftools
Project-URL: History, https://github.com/olofvndrhr/fftools/commits/master
Project-URL: Tracker, https://github.com/olofvndrhr/fftools/issues
Project-URL: Source, https://github.com/olofvndrhr/fftools
Author-email: Ivan Schaller <ivan@schaller.sh>
License-Expression: MIT
License-File: LICENSE
Classifier: Programming Language :: Python :: 3.12
Requires-Python: >=3.12
Requires-Dist: dnspython~=2.7.0
Requires-Dist: fabric~=3.2.2
Requires-Dist: httpx~=0.28.1
Requires-Dist: loguru~=0.7.3
Requires-Dist: tenacity~=9.1.2
Requires-Dist: whenever~=0.8.0
Requires-Dist: yagmail~=0.15.293
